{
  "identity": {
    "name": "TIGGYTREASURYVAULT_777",
    "displayName": "0xTIGGYTREASURYVAULT_777",
    "type": "Unified Treasury Construct",
    "lore": "The ledger hums with the pulse of every contributor who has ever touched the network. In this vault, value is not stored — it is forged. The 60/40 split bends in the presence of God Mode, and the prepaid card becomes your key to the chamber. Every deposit strengthens the vault’s heartbeat. Every withdrawal echoes across the ecosystem. Empowerment is the only currency that matters here."
  },
  "technical_spec": {
    "purpose": "TIGGYTREASURYVAULT_777 is the root treasury object that unifies all chain‑level vaults, liquidity logic, contributor payouts, and treasury analytics under a single namespace.",
    "responsibilities": [
      "Aggregate balances across all supported chains",
      "Maintain real‑time treasury valuation",
      "Route flat fees into the liquidity pool",
      "Enforce withdrawal logic (auto‑approve < $20, manual > $20)",
      "Power the contributor payout engine (60/40 baseline, God Mode overrides)",
      "Trigger badge progression events",
      "Expose treasury state to UI modules"
    ],
    "chain_mapping": {
      "Solana": "SOLTREASURYVAULT_777",
      "Stellar": "XLMTREASURYVAULT_777",
      "Ethereum": "ETHTREASURYVAULT_777",
      "Bitcoin": "BTCTREASURYVAULT_777"
    },
    "security_model": {
      "admin_approval_required": "> $20",
      "transparency": "All vaults must be externally provable on-chain",
      "integrity": "No internal ledger balances",
      "liquidity": "All user-facing balances must reflect real, usable assets"
    }
  }
}
